tinydic.py
TinyDIC-0.1.2.dist-info/METADATA
TinyDIC-0.1.2.dist-info/RECORD
TinyDIC-0.1.2.dist-info/WHEEL
TinyDIC-0.1.2.dist-info/top_level.txt
