Metadata-Version: 2.1
Name: TinyDIC
Version: 0.1.2
Summary: Tiny Python Dependency Injection Container.
Home-page: https://github.com/dareenzo/tinydic
Author: Paulo Phagula
Author-email: pphagula@gmail.com
License: See LICENSE
Keywords: dic,ioc,dependency injection,inversion of control
Platform: UNKNOWN
Classifier: Development Status :: 4 - Beta
Classifier: Intended Audience :: Developers
Classifier: Topic :: Software Development :: Libraries
Classifier: License :: OSI Approved :: MIT License
Classifier: Programming Language :: Python
